{
  "name": "Algox Stormcaller",
  "catchable": false,
  "flying": false,
  "deck": [
    "frosthaven",
    "decks",
    "boss"
  ],
  "image": "/frosthaven/monsters/algox-stormcaller.png",
  "boss": {
    "0": {
      "health": "Cx20",
      "shield": 0,
      "retaliate": {
        "range": 0,
        "value": 0
      },
      "movement": 2,
      "attack": "3",
      "attackModifiers": [],
      "immunities": [
        "immobilize",
        "disarm",
        "stun",
        "curse"
      ]
    },
    "1": {
      "health": "Cx20",
      "shield": 1,
      "retaliate": {
        "range": 0,
        "value": 0
      },
      "movement": 3,
      "attack": "3",
      "attackModifiers": [],
      "immunities": [
        "immobilize",
        "disarm",
        "stun",
        "curse"
      ]
    },
    "2": {
      "health": "Cx22",
      "shield": 1,
      "retaliate": {
        "range": 0,
        "value": 0
      },
      "movement": 3,
      "attack": "4",
      "attackModifiers": [],
      "immunities": [
        "immobilize",
        "disarm",
        "stun",
        "curse"
      ]
    },
    "3": {
      "health": "Cx26",
      "shield": 1,
      "retaliate": {
        "range": 0,
        "value": 0
      },
      "movement": 3,
      "attack": "4",
      "attackModifiers": [],
      "immunities": [
        "immobilize",
        "disarm",
        "stun",
        "curse"
      ]
    },
    "4": {
      "health": "Cx29",
      "shield": 1,
      "retaliate": {
        "range": 0,
        "value": 0
      },
      "movement": 3,
      "attack": "5",
      "attackModifiers": [],
      "immunities": [
        "immobilize",
        "disarm",
        "stun",
        "curse"
      ]
    },
    "5": {
      "health": "Cx29",
      "shield": 2,
      "retaliate": {
        "range": 0,
        "value": 0
      },
      "movement": 3,
      "attack": "5",
      "attackModifiers": [],
      "immunities": [
        "immobilize",
        "disarm",
        "stun",
        "curse"
      ]
    },
    "6": {
      "health": "Cx39",
      "shield": 2,
      "retaliate": {
        "range": 0,
        "value": 0
      },
      "movement": 3,
      "attack": "6",
      "attackModifiers": [],
      "immunities": [
        "immobilize",
        "disarm",
        "stun",
        "curse"
      ]
    },
    "7": {
      "health": "Cx44",
      "shield": 3,
      "retaliate": {
        "range": 0,
        "value": 0
      },
      "movement": 3,
      "attack": "7",
      "attackModifiers": [],
      "immunities": [
        "immobilize",
        "disarm",
        "stun",
        "curse"
      ]
    }
  }
}