{
  "name": "Harrower Infester",
  "catchable": false,
  "flying": false,
  "normal": {
    "0": {
      "health": 6,
      "shield": 0,
      "retaliate": {
        "range": 0,
        "value": 0
      },
      "movement": 2,
      "attack": 2,
      "attackModifiers": [],
      "immunities": []
    },
    "1": {
      "health": 7,
      "shield": 0,
      "retaliate": {
        "range": 0,
        "value": 1
      },
      "movement": 2,
      "attack": 2,
      "attackModifiers": [],
      "immunities": []
    },
    "2": {
      "health": 8,
      "shield": 0,
      "retaliate": {
        "range": 0,
        "value": 2
      },
      "movement": 2,
      "attack": 2,
      "attackModifiers": [],
      "immunities": []
    },
    "3": {
      "health": 10,
      "shield": 0,
      "retaliate": {
        "range": 0,
        "value": 2
      },
      "movement": 2,
      "attack": 3,
      "attackModifiers": [],
      "immunities": []
    },
    "4": {
      "health": 12,
      "shield": 0,
      "retaliate": {
        "range": 0,
        "value": 2
      },
      "movement": 3,
      "attack": 3,
      "attackModifiers": [],
      "immunities": []
    },
    "5": {
      "health": 12,
      "shield": 0,
      "retaliate": {
        "range": 0,
        "value": 3
      },
      "movement": 3,
      "attack": 4,
      "attackModifiers": [],
      "immunities": []
    },
    "6": {
      "health": 15,
      "shield": 0,
      "retaliate": {
        "range": 0,
        "value": 3
      },
      "movement": 3,
      "attack": 5,
      "attackModifiers": [],
      "immunities": []
    },
    "7": {
      "health": 18,
      "shield": 0,
      "retaliate": {
        "range": 0,
        "value": 4
      },
      "movement": 3,
      "attack": 5,
      "attackModifiers": [],
      "immunities": [
        "poison"
      ]
    }
  },
  "elite": {
    "0": {
      "health": 12,
      "shield": 0,
      "retaliate": {
        "range": 0,
        "value": 0
      },
      "movement": 2,
      "attack": 2,
      "attackModifiers": [],
      "immunities": []
    },
    "1": {
      "health": 12,
      "shield": 0,
      "retaliate": {
        "range": 0,
        "value": 2
      },
      "movement": 3,
      "attack": 2,
      "attackModifiers": [],
      "immunities": []
    },
    "2": {
      "health": 14,
      "shield": 0,
      "retaliate": {
        "range": 0,
        "value": 2
      },
      "movement": 3,
      "attack": 3,
      "attackModifiers": [],
      "immunities": []
    },
    "3": {
      "health": 17,
      "shield": 0,
      "retaliate": {
        "range": 0,
        "value": 3
      },
      "movement": 3,
      "attack": 3,
      "attackModifiers": [],
      "immunities": []
    },
    "4": {
      "health": 19,
      "shield": 0,
      "retaliate": {
        "range": 0,
        "value": 3
      },
      "movement": 3,
      "attack": 4,
      "attackModifiers": [],
      "immunities": []
    },
    "5": {
      "health": 21,
      "shield": 0,
      "retaliate": {
        "range": 0,
        "value": 3
      },
      "movement": 3,
      "attack": 5,
      "attackModifiers": [],
      "immunities": []
    },
    "6": {
      "health": 27,
      "shield": 0,
      "retaliate": {
        "range": 0,
        "value": 4
      },
      "movement": 3,
      "attack": 6,
      "attackModifiers": [],
      "immunities": [
        "poison"
      ]
    },
    "7": {
      "health": 32,
      "shield": 0,
      "retaliate": {
        "range": 0,
        "value": 4
      },
      "movement": 4,
      "attack": 6,
      "attackModifiers": [],
      "immunities": [
        "poison"
      ]
    }
  }
}